oblv_ctl/__init__.py
oblv_ctl/api/__init__.py
oblv_ctl/api/account/__init__.py
oblv_ctl/api/account/get_user_accounts_account_get.py
oblv_ctl/api/account/get_user_accounts_user_account_get.py
oblv_ctl/api/additional/__init__.py
oblv_ctl/api/additional/get_sample_service_content_sample_service_get.py
oblv_ctl/api/auth/__init__.py
oblv_ctl/api/auth/authenticate_key_login_apikey_post.py
oblv_ctl/api/auth/logout_session_logout_delete.py
oblv_ctl/api/deployment/__init__.py
oblv_ctl/api/deployment/add_deployment_tag_deployment_deployment_id_tag_post.py
oblv_ctl/api/deployment/create_new_deployment_deployment_post.py
oblv_ctl/api/deployment/create_new_deployment_deployment_static_post.py
oblv_ctl/api/deployment/delete_deployment_deployment_delete.py
oblv_ctl/api/deployment/generate_build_args_deployment_arguments_get.py
oblv_ctl/api/deployment/get_available_deployments_deployment_available_get.py
oblv_ctl/api/deployment/get_deployment_info_deployment_get.py
oblv_ctl/api/deployment/get_deployment_roles_deployment_roles_get.py
oblv_ctl/api/deployment/get_supported_regions_deployment_supported_regions_get.py
oblv_ctl/api/deployment/get_user_owned_deployments_deployment_owned_get.py
oblv_ctl/api/deployment/remove_deployment_tag_deployment_deployment_id_tag_delete.py
oblv_ctl/api/notification/__init__.py
oblv_ctl/api/notification/get_all_notifications_notification_get.py
oblv_ctl/api/notification/get_notification_details_notification_notification_id_get.py
oblv_ctl/api/notification/mark_all_notification_read_notification_delete.py
oblv_ctl/api/notification/mark_notification_read_notification_notification_id_delete.py
oblv_ctl/api/repo/__init__.py
oblv_ctl/api/repo/get_all_repos_repo_linked_get.py
oblv_ctl/api/repo/get_all_repos_user_repo_linked_get.py
oblv_ctl/api/repo/get_repo_dynamic_services_repo_service_dynamic_get.py
oblv_ctl/api/repo/get_repo_from_vcs_repo_get.py
oblv_ctl/api/repo/get_repo_refs_repo_refs_get.py
oblv_ctl/api/repo/get_repo_repo_repo_owner_repo_name_get.py
oblv_ctl-0.4.1.dist-info/entry_points.txt
oblv_ctl-0.4.1.dist-info/LICENSE
oblv_ctl-0.4.1.dist-info/METADATA
oblv_ctl-0.4.1.dist-info/WHEEL
oblv_ctl-0.4.1.dist-info/RECORD
