Metadata-Version: 2.1
Name: oblv-ctl
Version: 0.4.1
Summary: A client library for accessing Oblivious APIs
Home-page: https://github.com/ObliviousAI/oblv-ctl/tree/master/README.md
License: Apache-2.0
Keywords: Oblivious,python,package
Author: Oblivious Support
Author-email: support@oblivious.ai
Requires-Python: >=3.7,<4.0
Classifier: License :: OSI Approved :: Apache Software License
Classifier: Programming Language :: Python :: 3
Classifier: Programming Language :: Python :: 3.7
Classifier: Programming Language :: Python :: 3.8
Classifier: Programming Language :: Python :: 3.9
Classifier: Programming Language :: Python :: 3.10
Classifier: Programming Language :: Python :: 3.11
Requires-Dist: check-jsonschema (==0.22.0)
Requires-Dist: httpx (==0.15.0)
Requires-Dist: python-dateutil (==2.8.2)
Requires-Dist: requests (==2.29.0)
Requires-Dist: rich (>=11.1,<11.2)
Requires-Dist: typer (==0.7.0)
Project-URL: Repository, https://github.com/ObliviousAI/oblv-ctl
